piranha_playground/__init__.py
piranha_playground/data_validation.py
piranha_playground/main.py
piranha_playground/rule_inference/__init__.py
piranha_playground/rule_inference/controller.py
piranha_playground/rule_inference/graph_parser.py
piranha_playground/rule_inference/piranha_agent.py
piranha_playground/rule_inference/piranha_chat.py
piranha_playground/rule_inference/rule_application.py
piranha_playground/rule_inference/static_inference.py
piranha_playground/rule_inference/template_parser.py
piranha_playground/rule_inference/tests/__init__.py
piranha_playground/rule_inference/tests/test_codebase_refactorer.py
piranha_playground/rule_inference/tests/test_controller.py
piranha_playground/rule_inference/tests/test_graph_parser.py
piranha_playground/rule_inference/tests/test_inference.py
piranha_playground/rule_inference/tests/test_piranha_agent.py
piranha_playground/rule_inference/tests/test_server.py
piranha_playground/rule_inference/tests/test_template_parser.py
piranha_playground/rule_inference/utils/__init__.py
piranha_playground/rule_inference/utils/logger_formatter.py
piranha_playground/rule_inference/utils/node_utils.py
piranha_playground/rule_inference/utils/pretty_toml.py
piranha_playground/rule_inference/utils/rule_utils.py
piranha_playground/static/script.js
piranha_playground/static/styles.css
piranha_playground/templates/index.html
polyglot_piranha_playground-0.0.3.dist-info/METADATA
polyglot_piranha_playground-0.0.3.dist-info/WHEEL
polyglot_piranha_playground-0.0.3.dist-info/entry_points.txt
polyglot_piranha_playground-0.0.3.dist-info/top_level.txt
polyglot_piranha_playground-0.0.3.dist-info/RECORD
