Metadata-Version: 2.1
Name: polyglot-piranha-playground
Version: 0.0.3
Summary: A playground for Piranha
Home-page: https://github.com/uber/piranha
License: UNKNOWN
Platform: UNKNOWN
Classifier: Programming Language :: Python :: 3
Classifier: License :: OSI Approved :: Apache Software License
Classifier: Operating System :: OS Independent
Requires-Python: >=3.9
Requires-Dist: tree-sitter
Requires-Dist: tree-sitter-languages
Requires-Dist: attrs
Requires-Dist: openai
Requires-Dist: polyglot-piranha
Requires-Dist: toml
Requires-Dist: pytest
Requires-Dist: flask
Requires-Dist: flask-socketio
Requires-Dist: comby
Requires-Dist: eventlet
